dserestapi/__init__.py
dserestapi-0.3.4.dist-info/METADATA
dserestapi-0.3.4.dist-info/WHEEL
dserestapi-0.3.4.dist-info/top_level.txt
dserestapi-0.3.4.dist-info/RECORD
