Metadata-Version: 2.4
Name: dserestapi
Version: 0.3.4
Summary: NETVIBES / Data Science Experience REST API
Author-email: JLE69 <jonghyuk.lee@3ds.com>
License: NONE
Project-URL: Homepage, https://github.com/innovata/DSE-REST-API
Project-URL: Repository, https://github.com/innovata/DSE-REST-API
Classifier: Development Status :: 3 - Alpha
Classifier: Intended Audience :: Developers
Classifier: License :: OSI Approved :: MIT License
Classifier: Programming Language :: Python :: 3
Classifier: Programming Language :: Python :: 3.10
Classifier: Programming Language :: Python :: 3.11
Classifier: Programming Language :: Python :: 3.12
Requires-Python: >=3.10
Requires-Dist: requests
Requires-Dist: tqdm
